exchange_streamer/__init__.py
exchange_streamer/configuration/__init__.py
exchange_streamer/configuration/config.py
exchange_streamer/configuration/config_oci.py
exchange_streamer/db_management/__init__.py
exchange_streamer/db_management/redis_client.py
exchange_streamer/messaging/__init__.py
exchange_streamer/messaging/get_published_messages.py
exchange_streamer/messaging/telegram_bot.py
exchange_streamer/strategies/__init__.py
exchange_streamer/strategies/config_strategies.toml
exchange_streamer/streaming_data/__init__.py
exchange_streamer/streaming_data/data_producer_binance.py
exchange_streamer/transaction_management/api_url_end_point.toml
exchange_streamer/transaction_management/distributing_ws_data.py
exchange_streamer/transaction_management/download_binance.py
exchange_streamer/transaction_management/relaying_result.py
exchange_streamer/utilities/__init__.py
exchange_streamer/utilities/caching.py
exchange_streamer/utilities/number_modification.py
exchange_streamer/utilities/pickling.py
exchange_streamer/utilities/string_modification.py
exchange_streamer/utilities/system_tools.py
exchange_streamer/utilities/time_modification.py
exchange_streamer-0.2.94.dist-info/METADATA
exchange_streamer-0.2.94.dist-info/WHEEL
exchange_streamer-0.2.94.dist-info/RECORD
