Metadata-Version: 2.4
Name: exchange_streamer
Version: 0.2.94
Summary: Add your description here
Author-email: "ven.ajie" <venoajie@gmail.com>
Requires-Python: >=3.12
Requires-Dist: aioredis>=2.0.1
Requires-Dist: ccxt==4.4.74
Requires-Dist: dataclassy==1.0.1
Requires-Dist: httpx==0.27.2
Requires-Dist: loguru==0.7.3
Requires-Dist: orjson==3.10.15
Requires-Dist: python-dotenv==1.0.1
Requires-Dist: python-telegram-bot==22.0
Requires-Dist: redis[hiredis]>=5.2.1
Requires-Dist: tomli==2.0.2
Requires-Dist: uvloop>=0.21.0
Requires-Dist: websockets==15.0
